Workbook

Sheet Legend
A1: How to use this tracker
A2: 1. Unit Economics: fill the yellow cells (blue text) for each product with real supplier prices. Everything black is calculated.
A3: 2. Daily Log: one row per product per channel per day. Fill the blue columns (A-L) from Instagram/YouTube/Pinterest, Shopify, Meta Ads Manager and your supplier orders. Grey columns calculate.
A4: 3. Row 2 of the Daily Log is an EXAMPLE row with made-up numbers. Delete it once you start.
A5: Decision rules (from ADS.md): stop an ad at 2x break-even CPA with 0 purchases; scale 20-30% every 2 days while CPA < target CPA.
A6: Fees assumption: PayPal ~4.4% + $0.30 per order, plus Shopify 2% third-party gateway fee (Basic plan). Check current rates on PayPal and Shopify pricing pages.
A7: Meta ads billed in India carry 18% GST (claimable only if GST-registered).

Sheet Unit Economics
A1: Metric | B1: Product 1 | C1: Product 2 | D1: Product 3
A2: Product name | B2: Woven blanket | C2: Storybook | D2: Gift set (bundle)
A3: Single price ($) | B3: 64 | C3: 42 | D3: 99
A4: Product cost single ($) | B4: 28.85 | C4: 11.42 | D4: 40.27
A5: US shipping single ($) | B5: 10.39 | C5: 6.19 | D5: 12.79
A6: Upgrade price ($): bundle for blanket, +2nd copy for book | B6: 99 | C6: 61 | D6: 99
A7: Product cost upgrade ($) | B7: 40.27 | C7: 22.84 | D7: 40.27
A8: US shipping upgrade ($) | B8: 12.79 | C8: 8.59 | D8: 12.79
A9: Upgrade uptake (% of orders, assumption) | B9: 0.3 | C9: 0.2 | D9: 0
A10: Payment+platform fee (%) | B10: 0.065 | C10: 0.065 | D10: 0.065
A11: Fixed fee per order ($) | B11: 0.3 | C11: 0.3 | D11: 0.3
A12: GST on ads (%) | B12: 0.18 | C12: 0.18 | D12: 0.18
A13: Target profit per order ($) | B13: 6 | C13: 6 | D13: 6
A14: Margin single ($) | B14: =B3-B4-B5-B3*B10-B11 -> 20.3 | C14: =C3-C4-C5-C3*C10-C11 -> 21.36 | D14: =D3-D4-D5-D3*D10-D11 -> 39.205
A15: Margin bundle ($) | B15: =B6-B7-B8-B6*B10-B11 -> 39.205 | C15: =C6-C7-C8-C6*C10-C11 -> 25.305 | D15: =D6-D7-D8-D6*D10-D11 -> 39.205
A16: Blended margin ($) | B16: =(1-B9)*B14+B9*B15 -> 25.9715 | C16: =(1-C9)*C14+C9*C15 -> 22.149 | D16: =(1-D9)*D14+D9*D15 -> 39.205
A17: Blended avg order ($) | B17: =(1-B9)*B3+B9*B6 -> 74.5 | C17: =(1-C9)*C3+C9*C6 -> 45.8 | D17: =(1-D9)*D3+D9*D6 -> 99
A18: Break-even CPA (as shown in Meta, pre-GST) ($) | B18: =B16/(1+B12) -> 22.009746 | C18: =C16/(1+C12) -> 18.770339 | D18: =D16/(1+D12) -> 33.224576
A19: Target CPA (as shown in Meta, pre-GST) ($) | B19: =MAX(0,(B16-B13)/(1+B12)) -> 16.925 | C19: =MAX(0,(C16-C13)/(1+C12)) -> 13.685593 | D19: =MAX(0,(D16-D13)/(1+D12)) -> 28.139831
A20: Break-even ROAS (Meta, pre-GST) | B20: =IFERROR(B17/B18,0) -> 3.3848642 | C20: =IFERROR(C17/C18,0) -> 2.4400199 | D20: =IFERROR(D17/D18,0) -> 2.979722
A21: Target ROAS | B21: =IFERROR(B17/B19,0) -> 4.4017725 | C21: =IFERROR(C17/C19,0) -> 3.3465849 | D21: =IFERROR(D17/D19,0) -> 3.5181449

Sheet Daily Log
A1: Date | B1: Product (1/2/3) | C1: Channel | D1: Video/ad name | E1: Views / impressions | F1: Link clicks | G1: Store sessions | H1: Add to carts | I1: Orders | J1: Revenue ($) | K1: Ad spend ($, Meta pre-GST) | L1: Supplier cost for these orders ($) | M1: CTR | N1: Store conversion | O1: Cost per order (Meta, pre-GST) ($) | P1: ROAS | Q1: Gross margin ($) | R1: Profit after ads incl. GST ($) | S1: Status vs break-even
A2: 2026-10-20 | B2: 1 | C2: Instagram Reels | D2: 1A transformation | E2: 12000 | F2: 140 | G2: 120 | H2: 6 | I2: 1 | J2: 64 | K2: 0 | L2: 39.24 | M2: =IF(E2>0,F2/E2,"") -> 0.011666667 | N2: =IF(G2>0,I2/G2,"") -> 0.0083333333 | O2: =IF(AND(I2>0,K2>0),K2/I2,"") | P2: =IF(K2>0,J2/K2,"") | Q2: =IF(B2="","",J2-J2*INDEX('Unit Economics'!$B$10:$D$10,1,B2)-I2*INDEX('Unit Economics'!$B$11:$D$11,1,B2)-L2) -> 20.3 | R2: =IF(B2="","",Q2-K2*(1+INDEX('Unit Economics'!$B$12:$D$12,1,B2))) -> 20.3 | S2: =IF(O2="","",IF(O2<=INDEX('Unit Economics'!$B$19:$D$19,1,B2),"Scale",IF(O2<=INDEX('Unit Economics'!$B$18:$D$18,1,B2),"Keep","Losing money")))
M3: =IF(E3>0,F3/E3,"") | N3: =IF(G3>0,I3/G3,"") | O3: =IF(AND(I3>0,K3>0),K3/I3,"") | P3: =IF(K3>0,J3/K3,"") | Q3: =IF(B3="","",J3-J3*INDEX('Unit Economics'!$B$10:$D$10,1,B3)-I3*INDEX('Unit Economics'!$B$11:$D$11,1,B3)-L3) | R3: =IF(B3="","",Q3-K3*(1+INDEX('Unit Economics'!$B$12:$D$12,1,B3))) | S3: =IF(O3="","",IF(O3<=INDEX('Unit Economics'!$B$19:$D$19,1,B3),"Scale",IF(O3<=INDEX('Unit Economics'!$B$18:$D$18,1,B3),"Keep","Losing money")))
M4: =IF(E4>0,F4/E4,"") | N4: =IF(G4>0,I4/G4,"") | O4: =IF(AND(I4>0,K4>0),K4/I4,"") | P4: =IF(K4>0,J4/K4,"") | Q4: =IF(B4="","",J4-J4*INDEX('Unit Economics'!$B$10:$D$10,1,B4)-I4*INDEX('Unit Economics'!$B$11:$D$11,1,B4)-L4) | R4: =IF(B4="","",Q4-K4*(1+INDEX('Unit Economics'!$B$12:$D$12,1,B4))) | S4: =IF(O4="","",IF(O4<=INDEX('Unit Economics'!$B$19:$D$19,1,B4),"Scale",IF(O4<=INDEX('Unit Economics'!$B$18:$D$18,1,B4),"Keep","Losing money")))
M5: =IF(E5>0,F5/E5,"") | N5: =IF(G5>0,I5/G5,"") | O5: =IF(AND(I5>0,K5>0),K5/I5,"") | P5: =IF(K5>0,J5/K5,"") | Q5: =IF(B5="","",J5-J5*INDEX('Unit Economics'!$B$10:$D$10,1,B5)-I5*INDEX('Unit Economics'!$B$11:$D$11,1,B5)-L5) | R5: =IF(B5="","",Q5-K5*(1+INDEX('Unit Economics'!$B$12:$D$12,1,B5))) | S5: =IF(O5="","",IF(O5<=INDEX('Unit Economics'!$B$19:$D$19,1,B5),"Scale",IF(O5<=INDEX('Unit Economics'!$B$18:$D$18,1,B5),"Keep","Losing money")))
M6: =IF(E6>0,F6/E6,"") | N6: =IF(G6>0,I6/G6,"") | O6: =IF(AND(I6>0,K6>0),K6/I6,"") | P6: =IF(K6>0,J6/K6,"") | Q6: =IF(B6="","",J6-J6*INDEX('Unit Economics'!$B$10:$D$10,1,B6)-I6*INDEX('Unit Economics'!$B$11:$D$11,1,B6)-L6) | R6: =IF(B6="","",Q6-K6*(1+INDEX('Unit Economics'!$B$12:$D$12,1,B6))) | S6: =IF(O6="","",IF(O6<=INDEX('Unit Economics'!$B$19:$D$19,1,B6),"Scale",IF(O6<=INDEX('Unit Economics'!$B$18:$D$18,1,B6),"Keep","Losing money")))
M7: =IF(E7>0,F7/E7,"") | N7: =IF(G7>0,I7/G7,"") | O7: =IF(AND(I7>0,K7>0),K7/I7,"") | P7: =IF(K7>0,J7/K7,"") | Q7: =IF(B7="","",J7-J7*INDEX('Unit Economics'!$B$10:$D$10,1,B7)-I7*INDEX('Unit Economics'!$B$11:$D$11,1,B7)-L7) | R7: =IF(B7="","",Q7-K7*(1+INDEX('Unit Economics'!$B$12:$D$12,1,B7))) | S7: =IF(O7="","",IF(O7<=INDEX('Unit Economics'!$B$19:$D$19,1,B7),"Scale",IF(O7<=INDEX('Unit Economics'!$B$18:$D$18,1,B7),"Keep","Losing money")))
M8: =IF(E8>0,F8/E8,"") | N8: =IF(G8>0,I8/G8,"") | O8: =IF(AND(I8>0,K8>0),K8/I8,"") | P8: =IF(K8>0,J8/K8,"") | Q8: =IF(B8="","",J8-J8*INDEX('Unit Economics'!$B$10:$D$10,1,B8)-I8*INDEX('Unit Economics'!$B$11:$D$11,1,B8)-L8) | R8: =IF(B8="","",Q8-K8*(1+INDEX('Unit Economics'!$B$12:$D$12,1,B8))) | S8: =IF(O8="","",IF(O8<=INDEX('Unit Economics'!$B$19:$D$19,1,B8),"Scale",IF(O8<=INDEX('Unit Economics'!$B$18:$D$18,1,B8),"Keep","Losing money")))
M9: =IF(E9>0,F9/E9,"") | N9: =IF(G9>0,I9/G9,"") | O9: =IF(AND(I9>0,K9>0),K9/I9,"") | P9: =IF(K9>0,J9/K9,"") | Q9: =IF(B9="","",J9-J9*INDEX('Unit Economics'!$B$10:$D$10,1,B9)-I9*INDEX('Unit Economics'!$B$11:$D$11,1,B9)-L9) | R9: =IF(B9="","",Q9-K9*(1+INDEX('Unit Economics'!$B$12:$D$12,1,B9))) | S9: =IF(O9="","",IF(O9<=INDEX('Unit Economics'!$B$19:$D$19,1,B9),"Scale",IF(O9<=INDEX('Unit Economics'!$B$18:$D$18,1,B9),"Keep","Losing money")))
M10: =IF(E10>0,F10/E10,"") | N10: =IF(G10>0,I10/G10,"") | O10: =IF(AND(I10>0,K10>0),K10/I10,"") | P10: =IF(K10>0,J10/K10,"") | Q10: =IF(B10="","",J10-J10*INDEX('Unit Economics'!$B$10:$D$10,1,B10)-I10*INDEX('Unit Economics'!$B$11:$D$11,1,B10)-L10) | R10: =IF(B10="","",Q10-K10*(1+INDEX('Unit Economics'!$B$12:$D$12,1,B10))) | S10: =IF(O10="","",IF(O10<=INDEX('Unit Economics'!$B$19:$D$19,1,B10),"Scale",IF(O10<=INDEX('Unit Economics'!$B$18:$D$18,1,B10),"Keep","Losing money")))
M11: =IF(E11>0,F11/E11,"") | N11: =IF(G11>0,I11/G11,"") | O11: =IF(AND(I11>0,K11>0),K11/I11,"") | P11: =IF(K11>0,J11/K11,"") | Q11: =IF(B11="","",J11-J11*INDEX('Unit Economics'!$B$10:$D$10,1,B11)-I11*INDEX('Unit Economics'!$B$11:$D$11,1,B11)-L11) | R11: =IF(B11="","",Q11-K11*(1+INDEX('Unit Economics'!$B$12:$D$12,1,B11))) | S11: =IF(O11="","",IF(O11<=INDEX('Unit Economics'!$B$19:$D$19,1,B11),"Scale",IF(O11<=INDEX('Unit Economics'!$B$18:$D$18,1,B11),"Keep","Losing money")))
M12: =IF(E12>0,F12/E12,"") | N12: =IF(G12>0,I12/G12,"") | O12: =IF(AND(I12>0,K12>0),K12/I12,"") | P12: =IF(K12>0,J12/K12,"") | Q12: =IF(B12="","",J12-J12*INDEX('Unit Economics'!$B$10:$D$10,1,B12)-I12*INDEX('Unit Economics'!$B$11:$D$11,1,B12)-L12) | R12: =IF(B12="","",Q12-K12*(1+INDEX('Unit Economics'!$B$12:$D$12,1,B12))) | S12: =IF(O12="","",IF(O12<=INDEX('Unit Economics'!$B$19:$D$19,1,B12),"Scale",IF(O12<=INDEX('Unit Economics'!$B$18:$D$18,1,B12),"Keep","Losing money")))
M13: =IF(E13>0,F13/E13,"") | N13: =IF(G13>0,I13/G13,"") | O13: =IF(AND(I13>0,K13>0),K13/I13,"") | P13: =IF(K13>0,J13/K13,"") | Q13: =IF(B13="","",J13-J13*INDEX('Unit Economics'!$B$10:$D$10,1,B13)-I13*INDEX('Unit Economics'!$B$11:$D$11,1,B13)-L13) | R13: =IF(B13="","",Q13-K13*(1+INDEX('Unit Economics'!$B$12:$D$12,1,B13))) | S13: =IF(O13="","",IF(O13<=INDEX('Unit Economics'!$B$19:$D$19,1,B13),"Scale",IF(O13<=INDEX('Unit Economics'!$B$18:$D$18,1,B13),"Keep","Losing money")))
M14: =IF(E14>0,F14/E14,"") | N14: =IF(G14>0,I14/G14,"") | O14: =IF(AND(I14>0,K14>0),K14/I14,"") | P14: =IF(K14>0,J14/K14,"") | Q14: =IF(B14="","",J14-J14*INDEX('Unit Economics'!$B$10:$D$10,1,B14)-I14*INDEX('Unit Economics'!$B$11:$D$11,1,B14)-L14) | R14: =IF(B14="","",Q14-K14*(1+INDEX('Unit Economics'!$B$12:$D$12,1,B14))) | S14: =IF(O14="","",IF(O14<=INDEX('Unit Economics'!$B$19:$D$19,1,B14),"Scale",IF(O14<=INDEX('Unit Economics'!$B$18:$D$18,1,B14),"Keep","Losing money")))
... M401: =IF(E401>0,F401/E401,"") | N401: =IF(G401>0,I401/G401,"") | O401: =IF(AND(I401>0,K401>0),K401/I401,"") | P401: =IF(K401>0,J401/K401,"") | Q401: =IF(B401="","",J401-J401*INDEX('Unit Economics'!$B$10:$D$10,1,B401)-I401*INDEX('Unit Economics'!$B$11:$D$11,1,B401)-L401) | R401: =IF(B401="","",Q401-K401*(1+INDEX('Unit Economics'!$B$12:$D$12,1,B401))) | S401: =IF(O401="","",IF(O401<=INDEX('Unit Economics'!$B$19:$D$19,1,B401),"Scale",IF(O401<=INDEX('Unit Economics'!$B$18:$D$18,1,B401),"Keep","Losing money")))

Sheet Summary
A1: Totals by product
A2: Product | B2: Orders | C2: Revenue ($) | D2: Ad spend ($) | E2: Profit after ads ($) | F2: ROAS
A3: ='Unit Economics'!B2 -> Woven blanket | B3: =SUMIFS('Daily Log'!I:I,'Daily Log'!B:B,1) -> 1 | C3: =SUMIFS('Daily Log'!J:J,'Daily Log'!B:B,1) -> 64 | D3: =SUMIFS('Daily Log'!K:K,'Daily Log'!B:B,1) -> 0 | E3: =SUMIFS('Daily Log'!R:R,'Daily Log'!B:B,1) -> 20.3 | F3: =IF(D3>0,C3/D3,"")
A4: ='Unit Economics'!C2 -> Storybook | B4: =SUMIFS('Daily Log'!I:I,'Daily Log'!B:B,2) -> 0 | C4: =SUMIFS('Daily Log'!J:J,'Daily Log'!B:B,2) -> 0 | D4: =SUMIFS('Daily Log'!K:K,'Daily Log'!B:B,2) -> 0 | E4: =SUMIFS('Daily Log'!R:R,'Daily Log'!B:B,2) -> 0 | F4: =IF(D4>0,C4/D4,"")
A5: ='Unit Economics'!D2 -> Gift set (bundle) | B5: =SUMIFS('Daily Log'!I:I,'Daily Log'!B:B,3) -> 0 | C5: =SUMIFS('Daily Log'!J:J,'Daily Log'!B:B,3) -> 0 | D5: =SUMIFS('Daily Log'!K:K,'Daily Log'!B:B,3) -> 0 | E5: =SUMIFS('Daily Log'!R:R,'Daily Log'!B:B,3) -> 0 | F5: =IF(D5>0,C5/D5,"")
A6: Total | B6: =SUM(B3:B5) -> 1 | C6: =SUM(C3:C5) -> 64 | D6: =SUM(D3:D5) -> 0 | E6: =SUM(E3:E5) -> 20.3 | F6: =IF(D6>0,C6/D6,"")
